zapper/__init__.py
zapper/__main__.py
zapper/_common.py
zapper/_funcs.py
zapper/_helper.py
zapper/config.py
zapper/py.typed
zapper/_internal/__init__.py
zapper/_internal/_info.py
zapper/_internal/_version.py
zapper/_internal/_version.pyi
zapper/_internal/cli.py
zapper/_internal/cli_interactive.py
zapper/_internal/debug.py
zapper/core/__init__.py
zapper/core/_introspection.py
zapper/core/_worker.py
zapper/core/zapper_class.py
zapper/core/zapper_class.pyi
zapper/di/__init__.py
zapper/di/container.py
zapped-0.1.7.dist-info/METADATA
zapped-0.1.7.dist-info/WHEEL
zapped-0.1.7.dist-info/entry_points.txt
zapped-0.1.7.dist-info/RECORD
