Metadata-Version: 2.4
Name: zapped
Version: 0.1.7
Summary: A string manipulation tool for crazed maniacs including built in typed tuple returns.
Author-email: chaz <bright.lid5647@fastmail.com>
Requires-Python: >=3.13
Requires-Dist: alembic>=1.16.2
Requires-Dist: bear-utils>=0.10.8
Requires-Dist: dependency-injector>=4.48.1
Requires-Dist: pydantic>=2.11.5
Requires-Dist: python-dotenv>=1.1.0
Requires-Dist: singleton-base>=1.0.5
Requires-Dist: typer>=0.16.0
Requires-Dist: uv-dynamic-versioning>=0.11.0
